four_bit_ALU.v
module four_bit_alu(
    input  [3:0] A,
    input  [3:0] B,
    input  [2:0] sel,
    output reg [3:0] result,
    output reg carry
);

always @(*) begin

    carry = 0;

    case(sel)

        // Addition
        3'b000:
        begin
            {carry, result} = A + B;
        end

        // Subtraction
        3'b001:
        begin
            {carry, result} = A - B;
        end

        // AND
        3'b010:
        begin
            result = A & B;
        end

        // OR
        3'b011:
        begin
            result = A | B;
        end

        // XOR
        3'b100:
        begin
            result = A ^ B;
        end

        // NOT
        3'b101:
        begin
            result = ~A;
        end

        // Left Shift
        3'b110:
        begin
            result = A << 1;
        end

        // Right Shift
        3'b111:
        begin
            result = A >> 1;
        end

        default:
        begin
            result = 4'b0000;
            carry = 0;
        end

    endcase

end

endmodule

four_bit_ALU_tb.v
`timescale 1ns/1ps

module four_bit_alu_tb;

reg [3:0] A;
reg [3:0] B;
reg [2:0] sel;

wire [3:0] result;
wire carry;

// Instantiate ALU
four_bit_alu uut(
    .A(A),
    .B(B),
    .sel(sel),
    .result(result),
    .carry(carry)
);

initial begin

    // Generate waveform
    $dumpfile("four_bit_alu.vcd");
    $dumpvars(0, four_bit_alu_tb);

    $display("----------------------------------------------------------");
    $display("Time\tSel\tA\tB\tResult\tCarry");
    $display("----------------------------------------------------------");

    $monitor("%0t\t%b\t%b\t%b\t%b\t%b",
              $time, sel, A, B, result, carry);

    // Addition
    A = 4'b0101;
    B = 4'b0011;
    sel = 3'b000;
    #10;

    // Subtraction
    A = 4'b1000;
    B = 4'b0010;
    sel = 3'b001;
    #10;

    // AND
    A = 4'b1100;
    B = 4'b1010;
    sel = 3'b010;
    #10;

    // OR
    A = 4'b1100;
    B = 4'b1010;
    sel = 3'b011;
    #10;

    // XOR
    A = 4'b1100;
    B = 4'b1010;
    sel = 3'b100;
    #10;

    // NOT
    A = 4'b1010;
    B = 4'b0000;
    sel = 3'b101;
    #10;

    // Left Shift
    A = 4'b0011;
    B = 4'b0000;
    sel = 3'b110;
    #10;

    // Right Shift
    A = 4'b1100;
    B = 4'b0000;
    sel = 3'b111;
    #10;

    $finish;

end

endmodule

four_bit_alu.vcd
$date
	Tue Jul  7 00:06:05 2026
$end
$version
	Icarus Verilog
$end
$timescale
	1ps
$end
$scope module four_bit_alu_tb $end
$var wire 4 ! result [3:0] $end
$var wire 1 " carry $end
$var reg 4 # A [3:0] $end
$var reg 4 $ B [3:0] $end
$var reg 3 % sel [2:0] $end
$scope module uut $end
$var wire 4 & A [3:0] $end
$var wire 4 ' B [3:0] $end
$var wire 3 ( sel [2:0] $end
$var reg 1 " carry $end
$var reg 4 ) result [3:0] $end
$upscope $end
$upscope $end
$enddefinitions $end
$comment Show the parameter values. $end
$dumpall
$end
#0
$dumpvars
b1000 )
b0 (
b11 '
b101 &
b0 %
b11 $
b101 #
0"
b1000 !
$end
#10000
b110 !
b110 )
b1 %
b1 (
b10 $
b10 '
b1000 #
b1000 &
#20000
b1000 !
b1000 )
b10 %
b10 (
b1010 $
b1010 '
b1100 #
b1100 &
#30000
b1110 !
b1110 )
b11 %
b11 (
#40000
b110 !
b110 )
b100 %
b100 (
#50000
b101 !
b101 )
b101 %
b101 (
b0 $
b0 '
b1010 #
b1010 &
#60000
b110 !
b110 )
b110 %
b110 (
b11 #
b11 &
#70000
b111 %
b111 (
b1100 #
b1100 &
